{"InputTable": [{"Start": 12, "End": 44, "Value": "1234 Cherry Court\nGreensboro, VA"}, {"Start": 78, "End": 108, "Value": "789 Eighth Parkway\nVallejo, WY"}, {"Start": 135, "End": 162, "Value": "678 Redwood Lane\nPrague, KY"}, {"Start": 191, "End": 218, "Value": "123 Oak Road\nLouisville, FL"}, {"Start": 249, "End": 278, "Value": "456 Eighth Highway\nDenver, TN"}], "OutputTable": [{"Start": 42, "End": 44, "Value": "VA"}, {"Start": 106, "End": 108, "Value": "WY"}, {"Start": 160, "End": 162, "Value": "KY"}, {"Start": 216, "End": 218, "Value": "FL"}, {"Start": 276, "End": 278, "Value": "TN"}]}